shepherd_data/__init__.py
shepherd_data/cli.py
shepherd_data/ivonne.py
shepherd_data/mppt.py
shepherd_data/reader.py
shepherd_data-2025.8.1.dist-info/METADATA
shepherd_data-2025.8.1.dist-info/WHEEL
shepherd_data-2025.8.1.dist-info/entry_points.txt
shepherd_data-2025.8.1.dist-info/top_level.txt
shepherd_data-2025.8.1.dist-info/zip-safe
shepherd_data-2025.8.1.dist-info/RECORD
