Metadata-Version: 2.4
Name: shepherd_data
Version: 2025.8.1
Summary: Programming- and CLI-Interface for the h5-dataformat of the Shepherd-Testbed
Author-email: Ingmar Splitt <ingmar.splitt@tu-dresden.de>
Maintainer-email: Ingmar Splitt <ingmar.splitt@tu-dresden.de>
Project-URL: Documentation, https://github.com/nes-lab/shepherd-tools/blob/main/README.md
Project-URL: Issues, https://pypi.org/project/shepherd-data/issues
Project-URL: Source, https://pypi.org/project/shepherd-data/
Keywords: testbed,beaglebone,pru,batteryless,energyharvesting,solar
Platform: unix
Platform: linux
Platform: osx
Platform: cygwin
Platform: win32
Platform: win64
Classifier: Development Status :: 5 - Production/Stable
Classifier: Intended Audience :: Developers
Classifier: Intended Audience :: Information Technology
Classifier: Intended Audience :: Science/Research
Classifier: Programming Language :: Python :: 3.10
Classifier: Programming Language :: Python :: 3.11
Classifier: Programming Language :: Python :: 3.12
Classifier: Programming Language :: Python :: 3.13
Classifier: License :: OSI Approved :: MIT License
Classifier: Operating System :: OS Independent
Classifier: Natural Language :: English
Requires-Python: >=3.10
Requires-Dist: click
Requires-Dist: h5py
Requires-Dist: matplotlib
Requires-Dist: numpy
Requires-Dist: pandas>=2.0.0
Requires-Dist: pyYAML
Requires-Dist: scipy
Requires-Dist: shepherd-core[inventory]>=2025.08.1
Requires-Dist: tqdm
Provides-Extra: elf
Requires-Dist: shepherd-core[elf]; extra == "elf"
Provides-Extra: dev
Requires-Dist: shepherd-core[dev]; extra == "dev"
Requires-Dist: pandas-stubs; extra == "dev"
Provides-Extra: test
Requires-Dist: shepherd-core[test]; extra == "test"
Requires-Dist: pytest; extra == "test"
Requires-Dist: pytest-click; extra == "test"
Requires-Dist: coverage; extra == "test"
Provides-Extra: all
Requires-Dist: shepherd-data[dev,elf,test]; extra == "all"
